Workbook

Sheet Leyenda
A1: QUINOR S.A.C. - Backlog Alternativa 1 - Seguimiento de avance
A2: Sistema de deteccion de sustraccion de quinua en despacho. Documento Funcional y Tecnico v1.2.
A4: Estados de avance
A5: Estado | B5: Significado | C5: Cuando se usa
A6: NEW | B6: Planificada, sin bloqueo, aun no iniciada. | C6: Historia de un sprint futuro cuyas dependencias estan todas dentro de su propio sprint.
A7: PENDING | B7: Bloqueada: depende de historias de otro sprint. | C7: Regla del proyecto: no se cuenta en el sprint hasta que el sprint del que depende este DONE.
A8: ACTIVE | B8: En desarrollo en el sprint en curso. | C8: Historia del sprint actual sin dependencias cruzadas.
A9: DONE | B9: Terminada y con los tres criterios de aceptacion verificados. | C9: Se marca manualmente al cerrar la historia.
A11: Regla de dependencias aplicada
A12: - Una historia cuya dependencia vive en un sprint distinto al suyo se marca PENDING y no suma puntos al sprint.
A13: - Sprint en curso: 1. Las historias del Sprint 1 sin dependencia cruzada quedan ACTIVE.
A14: - HU-17 depende de HU-03 (Sprint 2), por eso queda PENDING pese a estar planificada en el Sprint 1.
A15: - La columna Estado es editable con lista desplegable. Actualizala conforme avance el desarrollo.
A16: - La hoja Resumen se recalcula sola a partir de la columna Estado.
A19: Hojas del libro
A20: Historias | B20: Las 14 historias del MVP con dependencias, estado y bloqueos.
A21: Backlog | B21: Las 6 historias postergadas fuera del MVP, con el motivo de cada una.
A22: Resumen | B22: Puntos e historias por sprint y por estado. Todo calculado con formulas.
A23: Tec_Sprint1 | B23: Verificacion de tecnologias necesarias para iniciar el Sprint 1.
A24: Hallazgos | B24: Inconsistencias detectadas en el documento funcional y su resolucion.

Sheet Historias
A1: Historias del MVP - Alternativa 1
A2: MVP de 14 historias (51 pts). Las 6 postergadas estan en la hoja Backlog. Columna Estado editable (NEW / PENDING / ACTIVE / DONE).
A4: ID | B4: Sprint | C4: Categoria | D4: Historia de usuario | E4: Criterios de aceptacion | F4: Prio. | G4: Pts. | H4: Depende de | I4: Sprint de cada dependencia | J4: Dependencia cruzada | K4: Estado | L4: Avance % | M4: Responsable | N4: Observaciones
A5: HU-01 | B5: 1 | C5: Captura de datos | D5: Como operador de despacho, quiero que el sistema registre automaticamente el peso de la bascula al cerrar cada carga, para no depender de anotaciones manuales que pueden alterarse. | E5: 1. Al finalizar la pesada, el sistema lee el peso via Modbus o serial y lo guarda con fecha, hora, ID de carga y ID de bascula. 2. Si la bascula no responde en 5 s se registra un error en la tabla salud_componente, expuesto por GET /salud. 3. El peso se almacena con dos decimales en kg. | F5: Must | G5: 3 | H5: Ninguna | I5: - | J5: No | K5: DONE | L5: 1 | N5: Entregada el 14/09/2026. Los tres criterios verificados con 29 pruebas automatizadas y 95% de cobertura. Ver README, apartado HU-01.
A6: HU-02 | B6: 1 | C6: Captura de datos | D6: Como operador de despacho, quiero que el sistema obtenga del ERP/WMS el peso y cantidad de sacos esperados de la orden de despacho, para comparar lo cargado contra lo planificado. | E6: 1. Dado un numero de orden, el sistema consulta el ERP por API REST y obtiene peso esperado y numero de sacos. 2. Si la orden no existe se muestra un mensaje y no se crea evento. 3. La respuesta se guarda junto a la pesada. | F6: Must | G6: 3 | H6: HU-01 | I6: HU-01 (S1) | J6: No | K6: DONE | L6: 1 | N6: Entregada el 14/09/2026. Los tres criterios verificados con 114 pruebas automatizadas y 100% de cobertura. Incluye la incidencia de integracion de la RN-02. Ver README, apartado HU-02.
A7: HU-03 | B7: 2 | C7: Deteccion | D7: Como supervisor de despacho, quiero que el sistema genere un evento de discrepancia cuando el peso real difiera del esperado mas alla de la tolerancia, para enterarme en el momento y no cuando reclama el cliente. | E7: 1. Si |peso real - peso esperado| > tolerancia configurada, se crea un evento con estado Pendiente. 2. El evento incluye orden, pesos, diferencia en kg y porcentaje. 3. La creacion del evento ocurre en menos de 10 s desde la pesada. | F7: Must | G7: 3 | H7: HU-01, HU-02, HU-04 | I7: HU-01 (S1), HU-02 (S1), HU-04 (S1) | J7: HU-01 (S1), HU-02 (S1), HU-04 (S1) | K7: DONE | L7: 1 | N7: Entregada el 14/09/2026, adelantada del Sprint 2. Sus tres dependencias (HU-01, HU-02 y HU-04) quedaron DONE al cerrar el Sprint 1, asi que dejo de estar bloqueada. Los tres criterios verificados con 337 pruebas automatizadas y 100% de cobertura. Evaluacion sincrona tras la pesada (milisegundos frente a los 10 s del criterio 3), un evento por pesada garantizado por clave unica, y las cargas sin tolerancia configurada se marcan como no evaluadas en lugar de pasar por limpias. Ver README, apartado HU-03.
A8: HU-04 | B8: 1 | C8: Configuracion | D8: Como administrador del sistema, quiero configurar la tolerancia de peso permitida (kg y porcentaje) por tipo de producto, para ajustar la sensibilidad sin cambiar el codigo. | E8: 1. Existe una pantalla de configuracion con campos de tolerancia en kg y %. 2. Solo el rol Administrador puede editarla. 3. Cada cambio queda registrado con usuario y fecha. | F8: Must | G8: 2 | H8: HU-14 | I8: HU-14 (S1) | J8: No | K8: DONE | L8: 1 | N8: Entregada el 14/09/2026. Los tres criterios verificados con 282 pruebas automatizadas y 100% de cobertura. Pantalla de tolerancias en el dashboard, edicion restringida a Administrador y cada cambio en auditoria con valores de antes y despues. Incluye la RN-01 (la mas restrictiva entre kg y %). Ver README, apartado HU-04.
A9: HU-05 | B9: 2 | C9: Captura de video | D9: Como supervisor de despacho, quiero que las camaras de la rampa graben de forma continua en un buffer circular, para contar con el video de cualquier carga reciente. | E9: 1. Cada camara RTSP se graba en segmentos de 1 min con el muxer segment de ffmpeg. 2. Se conservan al menos 72 h de video en disco local. 3. Si una camara se desconecta se registra en salud_componente, expuesto por GET /salud. | F9: Must | G9: 5 | H9: Ninguna | I9: - | J9: No | K9: DONE | L9: 1 | N9: Entregada el 14/09/2026, adelantada del Sprint 2. No tenia dependencias. Los tres criterios verificados con 89 pruebas automatizadas y 100% de cobertura, cuatro de ellas grabando video real por RTSP. Servicio propio en quinor/despacho/grabador: un ffmpeg por camara con el muxer segment, buffer circular de 72 h que libera espacio antes que dejar de grabar, y desconexion de camara visible en GET /salud. Incluye simulador de camaras RTSP. Ver README del grabador.
A10: HU-06 | B10: 2 | C10: Captura de video | D10: Como supervisor de despacho, quiero que el sistema recorte automaticamente el clip correspondiente a la ventana de tiempo de una carga con discrepancia, para revisar solo el tramo relevante y no horas de video. | E10: 1. Al crearse un evento se genera un clip desde 5 min antes del inicio de carga hasta 2 min despues del cierre. 2. El clip se guarda en MinIO y se vincula al evento. 3. Si falta video de ese rango, el evento se marca como Sin clip. | F10: Must | G10: 3 | H10: HU-03, HU-05 | I10: HU-03 (S2), HU-05 (S2) | J10: No | K10: DONE | L10: 1 | N10: Entregada el 14/09/2026. Sus dependencias HU-03 y HU-05 ya estaban DONE. Los tres criterios verificados con 514 pruebas automatizadas entre los dos servicios y 100% de cobertura, recortando video real y subiendolo a un S3 real. Repartida a proposito: la marca de inicio de carga vive en la API (nueva tabla carga y endpoint POST /cargas/{orden}/inicio) y el recorte en el grabador, que tiene el buffer y ffmpeg. El recorte espera a que se grabe el margen posterior al cierre. Ver README del grabador, apartado HU-06.
A11: HU-07 | B11: 3 | C11: Analisis IA | D11: Como supervisor de despacho, quiero que el sistema cuente los sacos cargados al camion a partir del video, para contrastar el conteo visual con el peso y la orden. | E11: 1. El servicio YOLO procesa el clip y devuelve el numero de sacos que cruzan la linea de carga. 2. La precision del conteo en el set de validacion es igual o mayor a 95%. 3. El conteo y la diferencia con la orden se guardan en el evento. | F11: Must | G11: 8 | H11: HU-06 | I11: HU-06 (S2) | J11: HU-06 (S2) | K11: DONE | L11: 1 | N11: Entregada el 16/09/2026, adelantada del Sprint 3. Su dependencia HU-06 ya estaba DONE. Los tres criterios verificados con 306 pruebas automatizadas entre el servicio YOLO (117) y el grabador (189), 100% de cobertura en ambos, modelo YOLO11n entrenado de verdad y analisis de video real. Criterio 2: precision media 100% sobre 8 cargas del set de validacion, con oclusiones y sacos que vuelven (reporte_validacion.txt). ADVERTENCIA: el set es sintetico porque QUINOR aun no entrego fotogramas de la rampa; mide el contador, no el modelo con sacos de yute reales. La cifra de planta sale del piloto, con el dataset de HU-19. Repartida: el conteo vive en el nuevo servicio quinor/despacho/yolo (POST /analisis/yolo) y la escritura en el evento en el grabador, que tiene el clip. Hallazgo: con salto de fotogramas 2 el conteo daba cero (ByteTrack perdia los sacos, no el detector); el valor por defecto paso a 1 y el fallo ahora se avisa en lugar de devolver un cero silencioso. Cambio de esquema: nueva columna evento.diferencia_sacos. Ver README de quinor/despacho/yolo.
A12: HU-08 | B12: 4 | C12: Analisis IA | D12: Como supervisor de despacho, quiero que el sistema haga seguimiento de las personas presentes en la zona de carga durante el evento, para identificar si hubo personal no autorizado o movimientos anomalos. | E12: 1. Se detecta y sigue a cada persona con un ID temporal durante el clip. 2. Se registra cuantas personas estuvieron en zona y el tiempo de permanencia. 3. No se realiza identificacion facial ni se guardan datos biometricos. | F12: Should | G12: 5 | H12: HU-06 | I12: HU-06 (S2) | J12: HU-06 (S2) | K12: DONE | L12: 1 | N12: Entregada el 16/09/2026, adelantada del Sprint 4. Su dependencia HU-06 ya estaba DONE. Los tres criterios verificados con 397 pruebas automatizadas entre el servicio YOLO (199), el grabador (198) y el orquestador (374 en total), 100% de cobertura en los tres, modelo entrenado y video real con operarios en el cuadro. Va en la misma pasada del video que HU-07: el clip ya esta abierto y ultralytics devuelve sacos y personas en la misma inferencia, asi que HU-08 no anade coste de GPU. Criterio 3 (sin identificacion facial ni biometria): se cumple por construccion, no por omision. De cada persona se guardan cuatro numeros (identificador del rastreador valido solo en ese clip, segundos en zona y dos fotogramas) y hay pruebas que vigilan la forma de los datos, de modo que anadir un recorte de imagen o un descriptor rompa la suite. Consecuencia asumida y documentada: si un operario sale del cuadro y vuelve se cuenta como dos presencias; es el precio de no identificar a nadie. Decisiones: la permanencia se mide dentro de una zona de carga configurable (ZONA_CARGA, se calibra en el piloto como la linea, apartado 9.1); "personal no habitual" de la RN-04 se resuelve con tres reglas por conteo y tiempo que no miran identidad (demasiadas personas a la vez, permanencia excesiva, gente sin sacos cruzando). Esa senal es el disparo que la RN-03 necesita para HU-09. Cambios de esquema: nueva tabla persona_en_evento y nueva columna evento.personal_anomalo (NULL mientras no se analiza, que no es lo mismo que False). Nuevo endpoint GET /eventos/{id}/personas y detalle en el dashboard con el aviso de que los identificadores son temporales. Ver README de quinor/despacho/yolo, apartado HU-08.
A13: HU-09 | B13: 4 | C13: Analisis IA | D13: Como supervisor de despacho, quiero que un modelo de vision-lenguaje describa lo ocurrido en el clip y asigne un nivel de severidad, para priorizar que eventos revisar primero. | E13: 1. Solo se invoca cuando YOLO confirma diferencia de sacos o personal anomalo. 2. La respuesta es un JSON con descripcion, severidad (Baja/Media/Alta) y evidencia observada. 3. Si la API falla se reintenta 3 veces y luego se marca Pendiente de analisis. | F13: Must | G13: 5 | H13: HU-07, HU-08 | I13: HU-07 (S3), HU-08 (S4) | J13: HU-07 (S3) | K13: DONE | L13: 1 | N13: Entregada el 17/09/2026, adelantada del Sprint 4. Sus dos dependencias, HU-07 y HU-08, ya estaban DONE. Los tres criterios verificados con 1029 pruebas automatizadas entre los cuatro servicios (vlm 185, yolo 222, grabador 240, orquestador 382), 100% de cobertura en los cuatro, y de punta a punta con el modelo YOLO entrenado, video real y el proveedor contestando por HTTP. Nuevo servicio quinor/despacho/vlm con POST /analisis/vlm (apartado 6.6). Va aparte no por tamano sino porque es el unico servicio que sale a internet: asi esa salida queda en un solo sitio que se puede cortar y vigilar. DECISION IMPORTANTE: la severidad del evento sale de la RN-04, que es una regla con umbrales exactos, y no del modelo. Una alerta de madrugada (HU-10) y el orden de la cola (HU-11) no pueden depender de la temperatura de un modelo, y "Alta porque la diferencia fue de 3 sacos" se puede comprobar; "Alta porque el modelo lo dijo" no. La del modelo se guarda aparte como severidad_ia y de comparar las dos sale la concordancia semanal del apartado 9.2. Consecuencia buena: la severidad existe aunque el proveedor este caido, que es el riesgo del apartado 12. Criterio 1 (RN-03): la puerta esta en app/invocacion.py. Ademas del costo hay otro motivo, que quedo documentado: un analisis que aparece en todos los eventos deja de leerse. Criterio 3: tres reintentos con espera creciente, distinguiendo lo que se arregla esperando (429, 503) de lo que no (401, 400); al agotarlos el evento pasa a pendiente_analisis y vuelve a pendiente al reintentar con exito, tal como el apartado 5.3. Se anadio tambien la extraccion de fotogramas clave en la misma pasada de YOLO, elegidos por lo que ocurre en ellos (saco saliente, pico de personas, primer y ultimo saco) y guardados en MinIO junto al clip: alimentan al modelo y dejan resuelto el criterio 3 de HU-12. Cambios de esquema: evento.descripcion_ia, evento.severidad y evento.fotogramas_clave. PENDIENTE: la clave de un proveedor real. Todo esta probado contra un stub que habla el mismo dialecto (sim/vlm_stub.py); la primera llamada de verdad espera a que QUINOR decida proveedor y provea la clave. Ver README de quinor/despacho/vlm.
A14: HU-10 | B14: 4 | C14: Alertas | D14: Como supervisor de despacho, quiero recibir una notificacion inmediata segun la severidad del evento, para actuar antes de que el contenedor salga de planta. | E14: 1. La notificacion se envia por correo en los tres niveles. Alta: a supervisores y administradores, con asunto marcado y prioridad alta; Media: a supervisores; Baja: a supervisores, con prioridad normal. 2. La notificacion incluye orden, diferencia y enlace al evento. 3. La notificacion se envia en menos de 60 s tras el analisis. | F14: Must | G14: 3 | H14: HU-09 | I14: HU-09 (S4) | J14: No | K14: DONE | L14: 1 | N14: Entregada el 18/09/2026, adelantada del Sprint 4. Su unica dependencia, HU-09, ya estaba DONE. CAMBIO DE ALCANCE acordado el 18/09/2026 y aplicado antes de desarrollar: esta historia queda solo con correo. Slack sale porque se esta evaluando Teams en su lugar, y el SMS sale con el: los dos son canales externos con proveedor, clave y costo por mensaje, y se evaluan juntos en una historia posterior. El criterio 1 se reescribio en consecuencia, aqui y en el documento funcional (apartados 2, 3, 5.2, 5.4 y 6.4). Los criterios 2 y 3 no cambian. DECISION IMPORTANTE: al quedarse las tres severidades en un solo canal, el criterio 1 se habria quedado sin contenido, porque las tres alertas serian el mismo correo, que es la forma mas rapida de que un supervisor deje de abrirlos. La severidad pasa a decidir a quien se avisa y con que urgencia: Alta a supervisores y administradores con asunto [ALERTA ALTA] y prioridad alta; Media y Baja solo a supervisores y con prioridad normal. El rol Consulta no recibe alertas de ningun nivel: es de solo lectura del dashboard y no le corresponde actuar sobre una carga. Los tres criterios verificados con 1220 pruebas automatizadas entre los cinco servicios (notificaciones 144, vlm 185, yolo 222, grabador 279, orquestador 390), 100% de cobertura en los cinco, y de punta a punta con MySQL, un buzon de correo real (mailpit) y el dashboard: el aviso salio 0,01 s despues del analisis, el correo llego a los dos supervisores y al administrador con X-Priority 1, la segunda vuelta del sondeo no mando un segundo correo, y los niveles Media y Baja salieron solo a supervisores y sin prioridad. Nuevo servicio quinor/despacho/notificaciones con POST /notificaciones (apartado 6.4, aiosmtplib). Va aparte por lo mismo que el de vision-lenguaje: es uno de los dos servicios que hablan con un servidor de fuera, y tenerlo aparte deja esa salida en un sitio que se puede cortar y vigilar. Los destinatarios salen de la tabla usuario de HU-14 y no de una lista en el entorno: dar de alta a alguien en el dashboard basta para que reciba alertas, y darlo de baja lo corta el mismo dia. Criterio 3: el reloj lo mide el grabador, que es el unico que sabe cuando quedo escrita la severidad, y el aviso sale en la misma pasada del analisis; esperar a la vuelta siguiente del sondeo gastaria media ventana sin hacer nada. El retraso real se guarda en notificacion.segundos_desde_analisis y se ve en el dashboard, de modo que el criterio se mide y no se supone. El correo no lleva fotogramas adjuntos: son imagenes de la zona de carga con personas dentro y el apartado 8 las quiere en la red interna; el enlace del criterio 2 lleva al dashboard, que pide sesion. Cambios de esquema: tabla notificacion, con clave unica (evento_id, canal) que impide el correo repetido en cada vuelta del sondeo. Un aviso fallido no cuenta como avisado y su fila se reemplaza en el siguiente intento: si contara, un relay caido un minuto dejaria un evento Alto sin correo para siempre. La columna canal se conserva aunque hoy solo valga 'correo', para que Teams o el SMS tengan su fila cuando entren. PENDIENTE: los datos del relay corporativo (host, puerto, credenciales y buzon de salida). Todo esta probado contra mailpit y contra un servidor SMTP real levantado en las pruebas; el primer correo de verdad espera a que QUINOR provea esos datos. Ver README de quinor/despacho/notificaciones.
A15: HU-11 | B15: 2 | C15: Dashboard | D15: Como supervisor de despacho, quiero ver la lista de eventos con filtros por fecha, orden, severidad y estado, para encontrar rapidamente los casos que debo atender. | E15: 1. La tabla muestra ID, fecha, orden, diferencia, severidad y estado. La columna severidad queda vacia hasta HU-09. 2. Los filtros se combinan y la tabla se actualiza en menos de 2 s. 3. Por defecto se muestran los eventos Pendientes de los ultimos 7 dias. | F15: Must | G15: 3 | H15: HU-03 | I15: HU-03 (S2) | J15: No | K15: DONE | L15: 1 | N15: Entregada el 03/10/2026, adelantada del Sprint 2. Su unica dependencia, HU-03, ya estaba DONE. Los tres criterios verificados con 433 pruebas en el orquestador, 100 % de cobertura, y de punta a punta contra MySQL con 800 eventos sembrados en 60 dias y el dashboard real. HALLAZGO IMPORTANTE: el listado que existia armaba cada fila con cuatro consultas (la pesada, la orden y dos lecturas de auditoria para la tolerancia aplicada y la ventana del clip). Con 200 filas eran mas de 800 consultas. Medido por HTTP contra 800 eventos: GET /eventos?limite=200 tardaba 0,55 s con ~801 consultas; la bandeja nueva tarda 0,02 s con 2. Hoy el criterio 2 se cumplia igual, pero crecia con el numero de filas, y la pantalla que mas se usa es la que peor envejece. Hay una prueba que cuenta las sentencias que llegan al motor y falla si alguien vuelve a leer algo por fila. DECISION: ruta nueva GET /eventos/bandeja en lugar de ampliar GET /eventos. Son dos cosas distintas: el detalle devuelve el evento completo y se paga una vez; la bandeja devuelve lo justo que la tabla pinta, paginado. La tolerancia aplicada y la ventana del clip no viajan en la fila justamente por eso, y el dashboard las pide con GET /eventos/{id} solo cuando alguien abre un evento. Criterio 3: los valores por defecto se aplican por campo y no en bloque. Pedir un estado concreto no arrastra la ventana de 7 dias, y filtrar por severidad libera el defecto de Pendiente, porque quien busca todas las Altas las quiere en cualquier estado. La respuesta declara en filtros.por_defecto cuales puso el sistema, y la pantalla lo dice: sin ese aviso, un supervisor que ve tres eventos puede irse creyendo que son todos los que existen. sin_defectos=true busca en todo el historico y es explicito a proposito, pensado para HU-15. Ademas de los filtros del criterio se anadieron paginacion con total, busqueda parcial del numero de orden (el supervisor recuerda 0148, no la orden entera) y un filtro de solo con faltante de sacos, que separa el hurto de bultos de la sustitucion de producto. El resumen cuenta aparte las cargas con peso corto y los sacos cuadrados, que es la firma de la sustitucion. Sin cambios de esquema: los indices ix_evento_estado_creado y ix_evento_severidad ya existian desde HU-03 y HU-09, y son los que sostienen los filtros por defecto. Desbloquea HU-12 (detalle), HU-13 (clasificar), HU-15 (reportes) y HU-20 (exportar).
A16: HU-12 | B16: 4 | C16: Dashboard | D16: Como supervisor de despacho, quiero abrir el detalle de un evento y reproducir su clip junto con el analisis, para verificar con mis propios ojos lo que reporto el sistema. | E16: 1. El detalle muestra pesos, conteo de sacos, personas detectadas, descripcion y severidad. 2. El clip se reproduce en el navegador con controles de pausa y avance. 3. Se muestra el fotograma donde se detecto la anomalia. | F16: Must | G16: 3 | H16: HU-06, HU-09, HU-11 | I16: HU-06 (S2), HU-09 (S4), HU-11 (S2) | J16: HU-06 (S2), HU-11 (S2) | K16: DONE | L16: 1 | N16: Entregada el 08/10/2026, adelantada del Sprint 4. Los tres criterios verificados: el detalle trae pesos, conteo, personas, descripcion y severidad en GET /eventos/{id}/detalle (tres consultas fijas, con una presencia y con cuarenta); el clip se reproduce en el navegador con un enlace firmado de MinIO que caduca a los 15 minutos, comprobado en Chromium con pausa y avance; y el fotograma de la anomalia se muestra y abre el reproductor en su segundo. 87 pruebas nuevas, cobertura 100 %. Aviso: el clip es Matroska (.mkv), que Chrome y Edge reproducen pero Firefox y Safari no; la pantalla lo advierte.
... A18: HU-14 | B18: 1 | C18: Seguridad | D18: Como administrador del sistema, quiero gestionar usuarios y roles (Administrador, Supervisor, Consulta), para que cada persona solo acceda a lo que le corresponde. | E18: 1. Se pueden crear, desactivar y asignar roles a usuarios. 2. El rol Consulta no puede cambiar estados ni configuraciones. 3. Las contrasenas se almacenan con hash bcrypt. 4. La autenticacion usa token opaco en tabla api_token, revocable desde el dashboard. | F18: Must | G18: 3 | H18: Ninguna | I18: - | J18: No | K18: DONE | L18: 1 | N18: Entregada el 14/09/2026. Los cuatro criterios verificados con 214 pruebas automatizadas y 100% de cobertura. Autenticacion por token opaco en la tabla api_token, con revocacion inmediata desde el dashboard. Ver README, apartado HU-14. 03/10/2026: renumerada desde HU-15 al redefinir el MVP de 14 historias. El codigo y los README aun la citan como HU-15.
A19: TOTAL | G19: =SUM(G5:G18)

Sheet Backlog
A1: Backlog post-MVP - historias postergadas
A2: 6 historias (17 pts) fuera del MVP. Columna Estado editable. La columna O explica por que se posterga cada una.
A4: ID | B4: Sprint | C4: Categoria | D4: Historia de usuario | E4: Criterios de aceptacion | F4: Prio. | G4: Pts. | H4: Depende de | I4: Sprint de cada dependencia | J4: Dependencia cruzada | K4: Estado | L4: Avance % | M4: Responsable | N4: Observaciones | O4: Motivo de postergacion
A5: HU-15 | B5: 5 | C5: Reportes | D5: Como gerente de operaciones, quiero generar un reporte semanal de discrepancias con totales por severidad, turno y estado, para medir la tendencia de perdidas y falsos positivos. | E5: 1. El reporte se genera en PDF y Excel desde el dashboard. 2. Incluye tabla resumen y grafico de eventos por dia. 3. Se puede elegir cualquier rango de fechas. | F5: Should | G5: 3 | H5: HU-11 | I5: HU-11 (S2) | J5: HU-11 (S2) | K5: PENDING | L5: 0 | N5: Postergada fuera del MVP el 03/10/2026. Renumerada desde HU-14 para que la hoja Historias quede sin huecos. Excluida del conteo del sprint: depende de historias de otro sprint. | O5: Mide tendencias de varias semanas; no hace falta para validar el MVP ni para actuar antes de que salga el contenedor.
A6: HU-16 | B6: 4 | C6: Seguridad | D6: Como auditor interno, quiero consultar el historial de acciones realizadas sobre cada evento, para contar con evidencia trazable ante una investigacion de personal. | E6: 1. Cada cambio de estado, comentario o configuracion queda en una tabla de auditoria inmutable. 2. El historial es visible en el detalle del evento. 3. Los registros de auditoria no pueden borrarse desde la aplicacion. | F6: Should | G6: 2 | H6: HU-13 | I6: HU-13 (S4) | J6: No | K6: PENDING | L6: 0 | N6: Excluida del conteo del sprint: depende de historias de otro sprint. 03/10/2026: HU-13 paso al Sprint 4, la dependencia deja de ser cruzada. | O6: Los criterios 1 y 3 ya los garantiza el motor (tabla auditoria y triggers). Solo falta mostrar el historial, que no afecta a ningun indicador del piloto.
A7: HU-17 | B7: 1 | C7: Plataforma | D7: Como administrador del sistema, quiero que el analisis de video se procese en cola con reintentos automaticos, para que una falla temporal no deje eventos sin analizar. | E7: 1. Cada analisis es una tarea Celery con hasta 3 reintentos y espera exponencial. 2. Las tareas fallidas quedan visibles en el panel de salud. 3. El orquestador nunca bloquea el registro de pesadas mientras analiza video. | F7: Must | G7: 3 | H7: HU-03 | I7: HU-03 (S2) | J7: HU-03 (S2) | K7: PENDING | L7: 0 | N7: Excluida del conteo del sprint: dependia de HU-03, del Sprint 2. Al 14/09/2026 esa dependencia esta DONE, asi que HU-17 ya no esta bloqueada y se puede planificar. Cambiar su estado a NEW es una decision de planificacion: subiria los puntos computables del Sprint 1 de 11 a 14. | O7: El bucle del grabador ya hace de worker con reintentos y el criterio 3 se cumple por estar en otro proceso. Su criterio 2 depende de HU-18. Queda PENDING por decision del usuario.
A8: HU-18 | B8: 5 | C8: Plataforma | D8: Como administrador del sistema, quiero ver un panel de salud con el estado de bascula, camaras, cola de tareas y servicios de IA, para detectar fallas del sistema antes de que se pierdan eventos. | E8: 1. Cada componente muestra estado OK, Advertencia o Error y ultima verificacion. 2. Un componente en Error genera una alerta al administrador. 3. El panel se actualiza cada 30 s. | F8: Should | G8: 3 | H8: HU-01, HU-05, HU-17 | I8: HU-01 (S1), HU-05 (S2), HU-17 (S1) | J8: HU-01 (S1), HU-05 (S2), HU-17 (S1) | K8: PENDING | L8: 0 | N8: Excluida del conteo del sprint: depende de historias de otro sprint. | O8: Depende de HU-17. Mientras tanto salud_componente y GET /salud registran los fallos.
A9: HU-19 | B9: 5 | C9: Analisis IA | D9: Como ingeniero de datos, quiero reentrenar el modelo YOLO con imagenes etiquetadas de sacos de quinua de la planta, para mejorar la precision del conteo con datos propios. | E9: 1. Existe un script que toma un dataset en formato YOLO y entrena un nuevo modelo. 2. El nuevo modelo solo se despliega si supera la precision del anterior en el set de validacion. 3. Se conserva el historial de versiones del modelo. | F9: Should | G9: 5 | H9: HU-07 | I9: HU-07 (S3) | J9: HU-07 (S3) | K9: PENDING | L9: 0 | N9: Desbloqueada el 16/09/2026: HU-07, su unica dependencia, esta DONE. Es ademas la que sustituye el set sintetico de validacion por el dataset real etiquetado de la rampa y versiona el modelo en la tabla modelo_version; mientras tanto el nombre del archivo de pesos hace de version y viaja en cada respuesta del servicio. | O9: Requiere el dataset real de sacos de yute que debe aportar QUINOR. Encaja despues del piloto.
A10: HU-20 | B10: 5 | C10: Reportes | D10: Como gerente de operaciones, quiero exportar la lista de eventos filtrada a CSV, para analizar la informacion en otras herramientas. | E10: 1. El boton Exportar respeta los filtros activos. 2. El archivo incluye todas las columnas del evento y su estado. 3. La exportacion de hasta 10 000 eventos tarda menos de 10 s. | F10: Could | G10: 1 | H10: HU-11 | I10: HU-11 (S2) | J10: HU-11 (S2) | K10: PENDING | L10: 0 | N10: Excluida del conteo del sprint: depende de historias de otro sprint. | O10: Prioridad Could, la menor del backlog. Analisis fuera del sistema.
A11: TOTAL | G11: =SUM(G5:G10)

Sheet Resumen
A1: Resumen de avance
A2: Calculado con formulas sobre las hojas Historias (MVP) y Backlog. Cambia un Estado alli y este resumen se actualiza.
A4: Historias por sprint y estado
A5: Sprint | B5: NEW | C5: PENDING | D5: ACTIVE | E5: DONE | F5: Total historias | G5: Puntos totales | H5: Puntos computables
A6: Sprint 1 | B6: =COUNTIFS(Historias!$B$5:$B$18,1,Historias!$K$5:$K$18,"NEW") | C6: =COUNTIFS(Historias!$B$5:$B$18,1,Historias!$K$5:$K$18,"PENDING") | D6: =COUNTIFS(Historias!$B$5:$B$18,1,Historias!$K$5:$K$18,"ACTIVE") | E6: =COUNTIFS(Historias!$B$5:$B$18,1,Historias!$K$5:$K$18,"DONE") | F6: =COUNTIFS(Historias!$B$5:$B$18,1) | G6: =SUMIFS(Historias!$G$5:$G$18,Historias!$B$5:$B$18,1) | H6: =SUMIFS(Historias!$G$5:$G$18,Historias!$B$5:$B$18,1)-SUMIFS(Historias!$G$5:$G$18,Historias!$B$5:$B$18,1,Historias!$K$5:$K$18,"PENDING")
A7: Sprint 2 | B7: =COUNTIFS(Historias!$B$5:$B$18,2,Historias!$K$5:$K$18,"NEW") | C7: =COUNTIFS(Historias!$B$5:$B$18,2,Historias!$K$5:$K$18,"PENDING") | D7: =COUNTIFS(Historias!$B$5:$B$18,2,Historias!$K$5:$K$18,"ACTIVE") | E7: =COUNTIFS(Historias!$B$5:$B$18,2,Historias!$K$5:$K$18,"DONE") | F7: =COUNTIFS(Historias!$B$5:$B$18,2) | G7: =SUMIFS(Historias!$G$5:$G$18,Historias!$B$5:$B$18,2) | H7: =SUMIFS(Historias!$G$5:$G$18,Historias!$B$5:$B$18,2)-SUMIFS(Historias!$G$5:$G$18,Historias!$B$5:$B$18,2,Historias!$K$5:$K$18,"PENDING")
A8: Sprint 3 | B8: =COUNTIFS(Historias!$B$5:$B$18,3,Historias!$K$5:$K$18,"NEW") | C8: =COUNTIFS(Historias!$B$5:$B$18,3,Historias!$K$5:$K$18,"PENDING") | D8: =COUNTIFS(Historias!$B$5:$B$18,3,Historias!$K$5:$K$18,"ACTIVE") | E8: =COUNTIFS(Historias!$B$5:$B$18,3,Historias!$K$5:$K$18,"DONE") | F8: =COUNTIFS(Historias!$B$5:$B$18,3) | G8: =SUMIFS(Historias!$G$5:$G$18,Historias!$B$5:$B$18,3) | H8: =SUMIFS(Historias!$G$5:$G$18,Historias!$B$5:$B$18,3)-SUMIFS(Historias!$G$5:$G$18,Historias!$B$5:$B$18,3,Historias!$K$5:$K$18,"PENDING")
A9: Sprint 4 | B9: =COUNTIFS(Historias!$B$5:$B$18,4,Historias!$K$5:$K$18,"NEW") | C9: =COUNTIFS(Historias!$B$5:$B$18,4,Historias!$K$5:$K$18,"PENDING") | D9: =COUNTIFS(Historias!$B$5:$B$18,4,Historias!$K$5:$K$18,"ACTIVE") | E9: =COUNTIFS(Historias!$B$5:$B$18,4,Historias!$K$5:$K$18,"DONE") | F9: =COUNTIFS(Historias!$B$5:$B$18,4) | G9: =SUMIFS(Historias!$G$5:$G$18,Historias!$B$5:$B$18,4) | H9: =SUMIFS(Historias!$G$5:$G$18,Historias!$B$5:$B$18,4)-SUMIFS(Historias!$G$5:$G$18,Historias!$B$5:$B$18,4,Historias!$K$5:$K$18,"PENDING")
A10: Sprint 5 | B10: =COUNTIFS(Historias!$B$5:$B$18,5,Historias!$K$5:$K$18,"NEW") | C10: =COUNTIFS(Historias!$B$5:$B$18,5,Historias!$K$5:$K$18,"PENDING") | D10: =COUNTIFS(Historias!$B$5:$B$18,5,Historias!$K$5:$K$18,"ACTIVE") | E10: =COUNTIFS(Historias!$B$5:$B$18,5,Historias!$K$5:$K$18,"DONE") | F10: =COUNTIFS(Historias!$B$5:$B$18,5) | G10: =SUMIFS(Historias!$G$5:$G$18,Historias!$B$5:$B$18,5) | H10: =SUMIFS(Historias!$G$5:$G$18,Historias!$B$5:$B$18,5)-SUMIFS(Historias!$G$5:$G$18,Historias!$B$5:$B$18,5,Historias!$K$5:$K$18,"PENDING")
A11: TOTAL | B11: =SUM(B6:B10) | C11: =SUM(C6:C10) | D11: =SUM(D6:D10) | E11: =SUM(E6:E10) | F11: =SUM(F6:F10) | G11: =SUM(G6:G10) | H11: =SUM(H6:H10)
A13: Puntos por estado
A14: Estado | B14: Historias | C14: Puntos | D14: % de los 51 pts
A15: NEW | B15: =COUNTIF(Historias!$K$5:$K$18,"NEW") | C15: =SUMIF(Historias!$K$5:$K$18,"NEW",Historias!$G$5:$G$18) | D15: =IFERROR(C15/$C$19,0)
A16: PENDING | B16: =COUNTIF(Historias!$K$5:$K$18,"PENDING") | C16: =SUMIF(Historias!$K$5:$K$18,"PENDING",Historias!$G$5:$G$18) | D16: =IFERROR(C16/$C$19,0)
A17: ACTIVE | B17: =COUNTIF(Historias!$K$5:$K$18,"ACTIVE") | C17: =SUMIF(Historias!$K$5:$K$18,"ACTIVE",Historias!$G$5:$G$18) | D17: =IFERROR(C17/$C$19,0)
A18: DONE | B18: =COUNTIF(Historias!$K$5:$K$18,"DONE") | C18: =SUMIF(Historias!$K$5:$K$18,"DONE",Historias!$G$5:$G$18) | D18: =IFERROR(C18/$C$19,0)
A19: TOTAL | B19: =SUM(B15:B18) | C19: =SUM(Historias!$G$5:$G$18) | D19: =IFERROR(C19/C19,0)
A21: Sprint 1 en detalle
A22: Historias planificadas en el Sprint 1 | B22: =COUNTIFS(Historias!$B$5:$B$18,1)
A23: Historias computables (no PENDING) | B23: =COUNTIFS(Historias!$B$5:$B$18,1)-COUNTIFS(Historias!$B$5:$B$18,1,Historias!$K$5:$K$18,"PENDING")
A24: Puntos planificados | B24: =SUMIFS(Historias!$G$5:$G$18,Historias!$B$5:$B$18,1)
A25: Puntos computables | B25: =SUMIFS(Historias!$G$5:$G$18,Historias!$B$5:$B$18,1)-SUMIFS(Historias!$G$5:$G$18,Historias!$B$5:$B$18,1,Historias!$K$5:$K$18,"PENDING")
A26: Puntos excluidos por dependencia cruzada | B26: =SUMIFS(Historias!$G$5:$G$18,Historias!$B$5:$B$18,1,Historias!$K$5:$K$18,"PENDING")
A27: Velocidad estimada del equipo (pts/sprint) | B27: 15 | C27: Supuesto del documento, seccion 10. Editable.
A28: Holgura del Sprint 1 (pts) | B28: =B27-B25
A30: Backlog post-MVP (hoja Backlog)
A31: Estado | B31: Historias | C31: Puntos | D31: % de los 17 pts
A32: NEW | B32: =COUNTIF(Backlog!$K$5:$K$10,"NEW") | C32: =SUMIF(Backlog!$K$5:$K$10,"NEW",Backlog!$G$5:$G$10) | D32: =IFERROR(C32/$C$36,0)
A33: PENDING | B33: =COUNTIF(Backlog!$K$5:$K$10,"PENDING") | C33: =SUMIF(Backlog!$K$5:$K$10,"PENDING",Backlog!$G$5:$G$10) | D33: =IFERROR(C33/$C$36,0)
A34: ACTIVE | B34: =COUNTIF(Backlog!$K$5:$K$10,"ACTIVE") | C34: =SUMIF(Backlog!$K$5:$K$10,"ACTIVE",Backlog!$G$5:$G$10) | D34: =IFERROR(C34/$C$36,0)
A35: DONE | B35: =COUNTIF(Backlog!$K$5:$K$10,"DONE") | C35: =SUMIF(Backlog!$K$5:$K$10,"DONE",Backlog!$G$5:$G$10) | D35: =IFERROR(C35/$C$36,0)
A36: TOTAL | B36: =SUM(B32:B35) | C36: =SUM(Backlog!$G$5:$G$10) | D36: =IFERROR(C36/C36,0)

Sheet Tec_Sprint1
A1: Verificacion de tecnologias para iniciar el Sprint 1
A2: Alcance evaluado: HU-01, HU-02, HU-04 y HU-14. HU-17 queda fuera por estar en PENDING (depende de HU-03, Sprint 2), por lo que Celery, Redis y Flower salen de la ruta critica del Sprint 1.
A4: Historia | B4: Necesidad | C4: Tecnologia | D4: Tipo | E4: En el documento | F4: Criticidad | G4: Como se instala | H4: Por que hace falta
A5: Transversal | B5: Servidor ASGI | C5: uvicorn[standard] | D5: Paquete Python | E5: No | F5: Bloqueante | G5: pip install 'uvicorn[standard]' | H5: FastAPI es un framework, no un servidor. El documento nombra FastAPI en 6.3 pero nunca el ASGI server, sin el la API no arranca.
A6: Transversal | B6: Driver MySQL 8 | C6: cryptography | D6: Paquete Python | E6: No | F6: Bloqueante | G6: pip install cryptography | H6: MySQL 8 usa caching_sha2_password por defecto. Sin este paquete PyMySQL falla en el primer connect contra el contenedor.
A7: Transversal | B7: Base de datos | C7: mysql:8.4 (contenedor) | D7: Contenedor Docker | E7: Si | F7: Bloqueante | G7: docker compose: image mysql:8.4, --character-set-server=utf8mb4 | H7: Confirmado por el usuario: la base de datos corre en Docker. Charset utf8mb4 y DATETIME(6) segun seccion 6.5.
A8: Transversal | B8: Entorno de contenedores | C8: Docker Desktop + WSL2 | D8: Infraestructura | E8: Parcial | F8: Bloqueante | G8: Instalacion en la maquina de desarrollo Windows | H8: El documento menciona Docker Compose en 6.7 pero no el runtime en el equipo de desarrollo.
A9: Transversal | B9: Configuracion y secretos | C9: pydantic-settings, python-dotenv | D9: Paquete Python | E9: No | F9: Bloqueante | G9: pip install pydantic-settings python-dotenv | H9: La seccion 8 exige que las claves vivan en variables de entorno o secretos de Docker, pero no asigna ninguna tecnologia.
A10: Transversal | B10: Migraciones | C10: alembic | D10: Paquete Python | E10: Si | F10: Necesaria | G10: pip install alembic && alembic init | H10: Ya declarado en 6.3. Configurar utf8mb4 y DATETIME(6) en el template de migracion.
A11: Transversal | B11: Logging estructurado | C11: structlog | D11: Paquete Python | E11: No | F11: Necesaria | G11: pip install structlog | H11: El documento no define ninguna tecnologia de observabilidad pese a que RNF-03 exige 99% de disponibilidad.
A12: Transversal | B12: Pruebas | C12: pytest-asyncio, pytest-cov | D12: Paquete Python | E12: No | F12: Necesaria | G12: pip install pytest-asyncio pytest-cov | H12: RNF-05 exige 70% de cobertura sobre endpoints async. El documento solo nombra pytest.
A13: Transversal | B13: Sincronizacion horaria | C13: NTP en servidor, bascula y camaras | D13: Infraestructura | E13: No | F13: Necesaria | G13: Configurar NTP en el servidor de planta | H13: El modelo de datos usa DATETIME(6) para correlacionar pesada y video. Sin relojes sincronizados esa precision no sirve. No aparece en el documento.
A14: HU-01 | B14: Lectura de bascula | C14: pymodbus[serial] | D14: Paquete Python | E14: Parcial | F14: Bloqueante | G14: pip install 'pymodbus[serial]' | H14: El documento dice pymodbus o pyserial. El extra [serial] es el que habilita RS-232 y trae pyserial.
A15: HU-01 | B15: Simulador de bascula | C15: pymodbus.server | D15: Paquete Python | E15: No | F15: Bloqueante | G15: Incluido en pymodbus; contenedor scale-sim en el compose | H15: Decision acordada: sin bascula fisica en el Sprint 1, HU-01 no es desarrollable sin un servidor Modbus simulado.
... A27: HU-17 | B27: Cola de tareas | C27: celery, redis, flower | D27: Paquete y contenedor | E27: Si | F27: Fuera de alcance | G27: Diferido: HU-17 esta en PENDING | H27: HU-17 depende de HU-03 (Sprint 2). Por la regla de dependencias sale del Sprint 1. Se recomienda dejar el contenedor redis:7-alpine en el compose para no rehacerlo despues.
A29: Conteo | E29: =COUNTIF(E5:E27,"No")&" ausentes del documento" | F29: =COUNTIF(F5:F27,"Bloqueante")&" bloqueantes"

Sheet Hallazgos
A1: Inconsistencias detectadas en el documento funcional
A2: Los ocho hallazgos fueron aplicados en la version 1.1 del documento funcional.
A4: # | B4: Ubicacion | C4: Hallazgo | D4: Resolucion acordada | E4: Estado
A5: 1 | B5: HU-17 / Seccion 10 | C5: HU-17 esta planificada en el Sprint 1 pero depende de HU-03, que pertenece al Sprint 2. En el Sprint 1 no existe ninguna tarea real que encolar. | D5: Se marca PENDING y sale del conteo del Sprint 1 (-3 pts). Se recomienda dejar el contenedor redis:7-alpine en el compose desde el inicio para no rehacer la infraestructura al llegar al Sprint 2. | E5: Aplicado v1.1
A6: 2 | B6: HU-01, criterio 2 | C6: Exige registrar el error de bascula en el panel de salud, que es HU-18 y se entrega en el Sprint 5. El criterio no es verificable en el Sprint 1. | D6: Reescrito: el error se registra en la tabla salud_componente y se expone por GET /salud. La visualizacion queda para HU-18. | E6: Aplicado v1.1
A7: 3 | B7: Seccion 6.3 | C7: La tabla de componentes y tecnologias no incluye servidor ASGI, libreria de autenticacion, gestion de configuracion, logging ni pandas. | D7: Agregar uvicorn[standard], passlib[bcrypt], pydantic-settings, python-dotenv, structlog y pandas a la tabla de la seccion 6.3. | E7: Aplicado v1.1
A8: 4 | B8: Seccion 6.5 | C8: El modelo de datos no contempla la tabla de tokens de acceso a la API, necesaria para HU-14 con autenticacion por token opaco revocable. | D8: Agregar la tabla api_token con id, usuario_id, token_hash, nombre, creado_en, expira_en, ultimo_uso_en, revocado_en y revocado_por. | E8: Aplicado v1.1
A9: 5 | B9: Seccion 6.7 | C9: La infraestructura no contempla los simuladores necesarios para desarrollar sin bascula ni ERP reales, ni el requisito de sincronizacion horaria. | D9: Agregar los contenedores scale-sim (pymodbus.server) y erp-mock (FastAPI), y el requisito de NTP en servidor, bascula y camaras. | E9: Aplicado v1.1
A10: 6 | B10: Seccion 8 | C10: Exige que las claves vivan en variables de entorno o secretos de Docker, pero no asigna ninguna tecnologia de gestion de configuracion. | D10: Nombrar pydantic-settings y python-dotenv como mecanismo de carga, y documentar que ningun secreto se versiona. | E10: Aplicado v1.1
A11: 7 | B11: Seccion 5.3 | C11: HU-06 marca el evento como 'Sin clip', pero ese estado no existe en la tabla de estados de un evento. | D11: Agregar el estado Sin clip a la tabla 5.3 o convertirlo en un campo booleano del evento. Se decide al llegar al Sprint 2. | E11: Aplicado v1.1
A12: 8 | B12: HU-05, criterio 1 | C12: Indica grabar segmentos de 1 min con OpenCV o ffmpeg. OpenCV reencodifica, consume CPU y pierde fotogramas en grabacion continua. | D12: Usar el muxer segment de ffmpeg con -c copy y -strftime 1 para nombrar cada segmento con su marca de tiempo. Aplica en el Sprint 2. | E12: Aplicado v1.1
